{
  "autores": [
    "Renata E.H.M.B. Osório",
    "Ademir Neves",
    "Tiago Pacheco Camargo",
    "Sandro L. Mireski",
    "Adailton J. Bortoluzzi",
    "Eduardo E. Castellano",
    "Wolfgang Haase",
    "Zbigniew Tomkowicz"
  ],
  "nome": "Synthesis, structure, magnetism, and hydrolase and catecholase activity of a new trinuclear copper(II) complex",
  "publicador": "Inorganica Chimica Acta (Testo Stampato)",
  "versao": "435",
  "paginas": "153-158",
  "ano": 2015,
  "link": "http://dx.doi.org/10.2174/1871520614666141130125148"
}
