{
  "autores": [
    "I. Kade",
    "M. Paixao",
    "O. Rodrigues",
    "E. Ibukun",
    "A. L. Braga",
    "G. Zeni",
    "C. Nogueira",
    "J. Rocha"
  ],
  "nome": "Studies on the antioxidant effect and interaction of diphenyl diselenide and dicholesteroyl diselenide with hepatic ?-aminolevulinic acid dehydratase and isoforms of lactate dehydrogenase",
  "publicador": "Toxicology In Vitro",
  "versao": "23",
  "paginas": "14 - 20",
  "ano": 2009,
  "link": "http://dx.doi.org/10.1016/j.tiv.2008.08.008"
}
